__init__.py
risk_atlas_nexus/__init__.py
risk_atlas_nexus/library.py
risk_atlas_nexus/metadata_base.py
risk_atlas_nexus/ai_risk_ontology/__init__.py
risk_atlas_nexus/ai_risk_ontology/datamodel/__init__.py
risk_atlas_nexus/ai_risk_ontology/datamodel/ai_risk_ontology.py
risk_atlas_nexus/ai_risk_ontology/schema/ai-risk-ontology.yaml
risk_atlas_nexus/ai_risk_ontology/schema/ai_csiro_rai.yaml
risk_atlas_nexus/ai_risk_ontology/schema/ai_eval.yaml
risk_atlas_nexus/ai_risk_ontology/schema/ai_intrinsic.yaml
risk_atlas_nexus/ai_risk_ontology/schema/ai_risk.yaml
risk_atlas_nexus/ai_risk_ontology/schema/ai_system.yaml
risk_atlas_nexus/ai_risk_ontology/schema/common.yaml
risk_atlas_nexus/ai_risk_ontology/schema/energy.yaml
risk_atlas_nexus/ai_risk_ontology/schema/eu_ai_act.yaml
risk_atlas_nexus/ai_risk_ontology/schema/semweb_context.yaml
risk_atlas_nexus/ai_risk_ontology/util/__init__.py
risk_atlas_nexus/ai_risk_ontology/util/air_2024_risks2linkml.py
risk_atlas_nexus/ai_risk_ontology/util/credo2linkml.py
risk_atlas_nexus/ai_risk_ontology/util/export_cypher.py
risk_atlas_nexus/ai_risk_ontology/util/export_graph.py
risk_atlas_nexus/ai_risk_ontology/util/export_risk_atlas_tex.py
risk_atlas_nexus/ai_risk_ontology/util/latex_dumper.py
risk_atlas_nexus/ai_risk_ontology/util/mitriskrepo2linkml.py
risk_atlas_nexus/ai_risk_ontology/util/nistUpdateLinkmlWithActions.py
risk_atlas_nexus/ai_risk_ontology/util/nistactions2linkml.py
risk_atlas_nexus/ai_risk_ontology/util/riskatlas2linkml.py
risk_atlas_nexus/ai_risk_ontology/util/lifting/__init__.py
risk_atlas_nexus/ai_risk_ontology/util/lifting/import_risk_mappings.py
risk_atlas_nexus/blocks/prompt_builder.py
risk_atlas_nexus/blocks/prompt_response_schema.py
risk_atlas_nexus/blocks/prompt_templates.py
risk_atlas_nexus/blocks/inference/__init__.py
risk_atlas_nexus/blocks/inference/base.py
risk_atlas_nexus/blocks/inference/ollama.py
risk_atlas_nexus/blocks/inference/params.py
risk_atlas_nexus/blocks/inference/postprocessing.py
risk_atlas_nexus-1.0.4.dist-info/licenses/LICENSE
risk_atlas_nexus-1.0.4.dist-info/METADATA
risk_atlas_nexus-1.0.4.dist-info/WHEEL
risk_atlas_nexus-1.0.4.dist-info/top_level.txt
risk_atlas_nexus-1.0.4.dist-info/RECORD
